finoptim-0.1.72.dist-info/METADATA
finoptim-0.1.72.dist-info/WHEEL
finoptim/cost_and_coverage.py
finoptim/final_results.py
finoptim/monte_carlo.py
finoptim/optimisation.py
finoptim/prices/aws.py
finoptim/prices/azure.py
finoptim/prices/__init__.py
finoptim/__init__.py
finoptim/__validations__.py
finoptim/rust_as_backend.cp312-win_amd64.pyd
finoptim-0.1.72.dist-info/RECORD
