Metadata-Version: 2.1
Name: finoptim
Version: 0.1.72
Classifier: Programming Language :: Python :: 3
Classifier: License :: OSI Approved :: MIT License
Classifier: Operating System :: OS Independent
Requires-Dist: numpy
Requires-Dist: pandas
Requires-Dist: httpx
Requires-Dist: requests
Requires-Dist: tabulate
Summary: A small package to do some finops optimisations
Author-email: Timothée Obrecht <timothee@obrecht.xyz>
Requires-Python: >=3.10
Project-URL: Homepage, https://github.com/tomtom-internal/sp-ccoe-finops-optimiser
Project-URL: Bug Tracker, https://github.com/tomtom-internal/sp-ccoe-finops-optimiser/issues
Project-URL: documentation, https://finoptim.readthedocs.io/en/latest/
